setup.py
udacityawsdistributions/Binomialdistribution.py
udacityawsdistributions/Gaussiandistribution.py
udacityawsdistributions/Generaldistribution.py
udacityawsdistributions/__init__.py
udacityawsdistributions.egg-info/PKG-INFO
udacityawsdistributions.egg-info/SOURCES.txt
udacityawsdistributions.egg-info/dependency_links.txt
udacityawsdistributions.egg-info/not-zip-safe
udacityawsdistributions.egg-info/top_level.txt